omnigen/__init__.py
omnigen/__main__.py
omnigen/cli/__init__.py
omnigen/cli/main.py
omnigen/core/__init__.py
omnigen/core/base.py
omnigen/core/circuit_breaker.py
omnigen/core/error_handler.py
omnigen/core/exceptions.py
omnigen/core/health_check.py
omnigen/core/key_manager.py
omnigen/core/metrics.py
omnigen/core/provider_config.py
omnigen/core/provider_helper.py
omnigen/core/region_config.py
omnigen/core/types.py
omnigen/core/validators.py
omnigen/monitoring/__init__.py
omnigen/monitoring/health_check.py
omnigen/monitoring/metrics.py
omnigen/monitoring/mongodb_monitor.py
omnigen/pipelines/__init__.py
omnigen/pipelines/conversation_extension/__init__.py
omnigen/pipelines/conversation_extension/checkpoint.py
omnigen/pipelines/conversation_extension/config.py
omnigen/pipelines/conversation_extension/conversation_validators.py
omnigen/pipelines/conversation_extension/generator.py
omnigen/pipelines/conversation_extension/pipeline.py
omnigen/pipelines/conversation_extension/prompts.py
omnigen/pipelines/conversation_extension/runner.py
omnigen/pipelines/conversation_extension/streaming_loader.py
omnigen/pipelines/text_enhancement/__init__.py
omnigen/pipelines/text_enhancement/checkpoint.py
omnigen/pipelines/text_enhancement/config.py
omnigen/pipelines/text_enhancement/generator.py
omnigen/pipelines/text_enhancement/pipeline.py
omnigen/pipelines/text_enhancement/prompts.py
omnigen/pipelines/text_enhancement/runner.py
omnigen/pipelines/text_enhancement/streaming_loader.py
omnigen/pipelines/text_enhancement/validators.py
omnigen/providers/__init__.py
omnigen/providers/anthropic.py
omnigen/providers/async_anthropic.py
omnigen/providers/async_openai.py
omnigen/providers/async_openrouter.py
omnigen/providers/async_ultrasafe.py
omnigen/providers/base.py
omnigen/providers/factory.py
omnigen/providers/openai.py
omnigen/providers/openrouter.py
omnigen/providers/provider_pool.py
omnigen/providers/ultrasafe.py
omnigen/storage/incremental_saver.py
omnigen/utils/__init__.py
omnigen_usf-1.0.8.dist-info/licenses/LICENSE
omnigen_usf-1.0.8.dist-info/METADATA
omnigen_usf-1.0.8.dist-info/WHEEL
omnigen_usf-1.0.8.dist-info/entry_points.txt
omnigen_usf-1.0.8.dist-info/top_level.txt
omnigen_usf-1.0.8.dist-info/RECORD
