Metadata-Version: 2.4
Name: omnigen-usf
Version: 1.0.8
Summary: Enterprise-Grade Synthetic Data Generation with Production-Ready Configs, Complete Validation Rules, and Auto-Resume
Author-email: Ultrasafe AI <support@us.inc>
Maintainer-email: Ultrasafe AI <support@us.inc>
License: MIT
Project-URL: Homepage, https://us.inc
Project-URL: Documentation, https://github.com/ultrasafe-ai/omnigen
Project-URL: Repository, https://github.com/ultrasafe-ai/omnigen
Keywords: synthetic-data,data-generation,conversational-ai,text-enhancement,llm,pipeline,conversation-extension,pre-training,continual-pre-training,auto-resume,graceful-shutdown,machine-learning,ai
Classifier: Development Status :: 4 - Beta
Classifier: Intended Audience :: Developers
Classifier: Intended Audience :: Science/Research
Classifier: License :: OSI Approved :: MIT License
Classifier: Programming Language :: Python :: 3
Classifier: Programming Language :: Python :: 3.8
Classifier: Programming Language :: Python :: 3.9
Classifier: Programming Language :: Python :: 3.10
Classifier: Programming Language :: Python :: 3.11
Classifier: Programming Language :: Python :: 3.12
Classifier: Topic :: Scientific/Engineering :: Artificial Intelligence
Requires-Python: >=3.8
License-File: LICENSE
Requires-Dist: openai>=1.0.0
Requires-Dist: pyyaml>=6.0
Requires-Dist: tqdm>=4.65.0
Requires-Dist: pytz>=2023.3
Requires-Dist: python-dotenv>=1.0.0
Requires-Dist: typer>=0.9.0
Requires-Dist: pymongo>=4.0.0
Requires-Dist: datasets>=2.14.0
Requires-Dist: huggingface_hub>=0.16.0
Provides-Extra: hf
Requires-Dist: datasets>=2.14.0; extra == "hf"
Requires-Dist: huggingface_hub>=0.16.0; extra == "hf"
Provides-Extra: dev
Requires-Dist: pytest>=7.4.0; extra == "dev"
Requires-Dist: pytest-cov>=4.1.0; extra == "dev"
Requires-Dist: black>=23.0.0; extra == "dev"
Requires-Dist: ruff>=0.0.280; extra == "dev"
Requires-Dist: mypy>=1.5.0; extra == "dev"
Dynamic: license-file
